hextractor/__init__.py
hextractor/data_sources.py
hextractor/examples/__init__.py
hextractor/examples/data.py
hextractor/examples/langchain_integration.py
hextractor/examples/multi_table.py
hextractor/examples/single_table.py
hextractor/examples/utils.py
hextractor/extraction.py
hextractor/integrations/__init__.py
hextractor/integrations/langchain_graphdoc.py
hextractor/structures.py
hextractor/visualization.py
hextractor-1.0.2.dist-info/LICENSE
hextractor-1.0.2.dist-info/METADATA
hextractor-1.0.2.dist-info/WHEEL
hextractor-1.0.2.dist-info/RECORD
