Metadata-Version: 2.1
Name: hextractor
Version: 1.0.2
Summary: HeXtractor is a tool designed to automatically convert selected data in tabular format into a PyTorch Geometric heterogeneous graph. As research into graph neural networks (GNNs) expands, the importance of heterogeneous graphs grows. However, data often comes in tabular form, and manually transforming this data into graph format can be tedious and error-prone. HeXtractor aims to streamline this process, providing researchers and practitioners with a more efficient workflow.
License: BSD-3-Clause
Keywords: graphs,neural networks
Author: Filip
Author-email: filip.wojcik@outlook.com
Requires-Python: >=3.11,<4.0
Classifier: License :: OSI Approved :: BSD License
Classifier: Programming Language :: Python :: 3
Classifier: Programming Language :: Python :: 3.11
Classifier: Programming Language :: Python :: 3.12
Requires-Dist: autoroot (>=1.0.0,<2.0.0)
Requires-Dist: black (>=24.4.2,<25.0.0)
Requires-Dist: langchain-community (>=0.3.20,<0.4.0)
Requires-Dist: langchain-experimental (>=0.3.4,<0.4.0)
Requires-Dist: langchain-openai (>=0.3.9,<0.4.0)
Requires-Dist: pandas (>=2.2.2,<3.0.0)
Requires-Dist: pydantic (>=2.7.3,<3.0.0)
Requires-Dist: pyvis (>=0.3.2,<0.4.0)
Requires-Dist: torch (>=2.3.1,<3.0.0)
Requires-Dist: torch-geometric (>=2.5.3,<3.0.0)
Project-URL: Bug Tracker, https://github.com/maddataanalyst/hextractor/issues
Project-URL: documentation, https://hextractor.readthedocs.io/en/latest/
Project-URL: homepage, https://github.com/maddataanalyst/hextractor
Project-URL: repository, https://github.com/maddataanalyst/hextractor
